uv_audit/__init__.py
uv_audit/__main__.py
uv_audit/cli.py
uv_audit/manager.py
uv_audit/scan/__init__.py
uv_audit/scan/base.py
uv_audit/scan/safery.py
uv_audit-0.1.9.dist-info/METADATA
uv_audit-0.1.9.dist-info/WHEEL
uv_audit-0.1.9.dist-info/entry_points.txt
uv_audit-0.1.9.dist-info/top_level.txt
uv_audit-0.1.9.dist-info/RECORD
