Metadata-Version: 2.1
Name: uv-audit
Version: 0.1.9
Summary: uv Tool for checking dependencies for vulnerabilities
Author-email: Alekse Marusich <alekse.marusich@rocshers.com>
License: MIT
Keywords: rocshers,uvxt,packaging,audit
Classifier: License :: OSI Approved :: MIT License
Classifier: Intended Audience :: Developers
Classifier: Intended Audience :: Information Technology
Classifier: Intended Audience :: System Administrators
Classifier: Operating System :: OS Independent
Classifier: Topic :: Software Development :: Build Tools
Classifier: Topic :: Software Development :: Libraries :: Python Modules
Classifier: Topic :: Software Development :: Libraries
Classifier: Topic :: Software Development
Classifier: Topic :: System :: Archiving :: Packaging
Classifier: Topic :: System :: Installation/Setup
Classifier: Topic :: System :: Software Distribution
Classifier: Programming Language :: Python :: 3 :: Only
Classifier: Programming Language :: Python :: 3.9
Classifier: Programming Language :: Python :: 3
Classifier: Programming Language :: Python
Requires-Python: >=3.9
Requires-Dist: ijson >=3.3.0
Requires-Dist: package-schemes >=0.1.2
Requires-Dist: packaging >=24.2
Requires-Dist: pydantic >=2.9.2
Requires-Dist: safety-db
Requires-Dist: toml >=0.10.2
Requires-Dist: typer >=0.13.0
